is_valid_date/__init__.py
is_valid_date-0.4.0.dist-info/LICENSE.txt
is_valid_date-0.4.0.dist-info/METADATA
is_valid_date-0.4.0.dist-info/WHEEL
is_valid_date-0.4.0.dist-info/top_level.txt
is_valid_date-0.4.0.dist-info/RECORD
