Metadata-Version: 2.1
Name: is-valid-date
Version: 0.4.0
Summary: Check if a date is valid
Home-page: https://github.com/rogervila/python_is_valid_date
Download-URL: https://github.com/rogervila/python_is_valid_date/archive/0.4.0.tar.gz
Author: Roger Vilà
Author-email: rogervila@me.com
License: MIT
Keywords: valid date,check date,validate date
Platform: UNKNOWN
Classifier: Development Status :: 5 - Production/Stable
Classifier: Intended Audience :: Developers
Classifier: Topic :: Software Development :: Build Tools
Classifier: License :: OSI Approved :: MIT License
Classifier: Programming Language :: Python :: 3.9
License-File: LICENSE.txt
Requires-Dist: python-dateutil (<3,>=2)
